{"category":"Pokemon","id":"xy9-123","illustrator":"Mitsuhiro Arita","localId":"123","name":"Garados EX","rarity":"Secret Rare","set":{"cardCount":{"official":122,"total":123},"id":"xy9","name":"TURBOfieber","symbol":"https://assets.tcgdex.net/univ/xy/xy9/symbol"},"variants":{"firstEdition":false,"holo":true,"normal":true,"reverse":true},"dexId":[130],"hp":180,"types":["Water"],"suffix":"EX","attacks":[{"cost":["Colorless"],"name":"Stürmische See","effect":"Wirf so lang 1 Münze, bis zum ersten Mal das Ergebnis „Zahl“ kommt. Durchsuche pro „Kopf“ dein Deck nach 1 Water-Energiekarte und lege sie an dieses Pokémon an. Mische anschließend dein Deck."},{"cost":["Water","Water","Colorless","Colorless"],"name":"Verbrühung","effect":"Dieser Angriff fügt jedem Pokémon auf deiner Bank 10 Schadenspunkte zu. (Wende Schwäche und Resistenz bei Pokémon auf der Bank nicht an.)","damage":130}],"weaknesses":[{"type":"Lightning","value":"×2"}],"retreat":4,"legal":{"standard":false,"expanded":true}}