{"category":"Pokémon","id":"xy10-8","illustrator":"Kanako Eo","localId":"8","name":"Deerling","rarity":"Commún","set":{"cardCount":{"official":124,"total":125},"id":"xy10","name":"Destinos Enfrentados","symbol":"https://assets.tcgdex.net/univ/xy/xy10/symbol"},"variants":{"firstEdition":false,"holo":true,"normal":true,"reverse":true},"dexId":[585],"hp":60,"types":["Planta"],"stage":"Basico","attacks":[{"cost":["Incolora"],"name":"Encontrar un Amigo","effect":"Busca en tu baraja 1 Pokémon, enséñalo y ponlo en tu mano. Baraja las cartas de tu baraja después."}],"weaknesses":[{"type":"Guego","value":"×2"}],"retreat":1,"legal":{"standard":false,"expanded":true}}