{"category":"Pokémon","id":"xy12-1","illustrator":"Eske Yoshinob","localId":"1","name":"Bisaflor EX","rarity":"ultraselten","set":{"cardCount":{"official":108,"total":113},"id":"xy12","name":"Evolution","symbol":"https://assets.tcgdex.net/univ/xy/xy12/symbol"},"variants":{"firstEdition":false,"holo":true,"normal":true,"reverse":true},"dexId":[3],"hp":180,"types":["Pflanze"],"suffix":"EX","attacks":[{"cost":["Pflanze","Farblos","Farblos"],"name":"Giftpuder","effect":"Das Aktive Pokémon deines Gegners ist jetzt vergiftet.","damage":60},{"cost":["Pflanze","Pflanze","Farblos","Farblos"],"name":"Dschungel-Hammer","effect":"Heile 30 Schadenspunkte bei diesem Pokémon.","damage":90}],"weaknesses":[{"type":"Feuer","value":"×2"}],"retreat":4,"legal":{"standard":false,"expanded":true}}