{"category":"Pokémon","id":"bw7-22","illustrator":"Akira Komayama","localId":"22","name":"Camerupt","rarity":"Keine","set":{"cardCount":{"official":149,"total":153},"id":"bw7","name":"Überschrittene Schwellen","symbol":"https://assets.tcgdex.net/univ/bw/bw7/symbol"},"variants":{"firstEdition":false,"holo":true,"normal":true,"reverse":true},"dexId":[323],"hp":130,"types":["Feuer"],"stage":"Rang 1","attacks":[{"cost":["Feuer","Farblos","Farblos"],"damage":60},{"cost":["Feuer","Feuer","Farblos","Farblos"],"damage":80}],"weaknesses":[{"type":"Wasser","value":"×2"}],"retreat":4,"legal":{"standard":false,"expanded":true}}