{"cards":[{"id":"hgss3-45","localId":"45","name":"Doduo"},{"id":"g1-55","image":"https://assets.tcgdex.net/fr/xy/g1/55","localId":"55","name":"Doduo"},{"id":"xy12-69","image":"https://assets.tcgdex.net/fr/xy/xy12/69","localId":"69","name":"Doduo"},{"id":"xy1-98","image":"https://assets.tcgdex.net/fr/xy/xy1/98","localId":"98","name":"Doduo"},{"id":"bw8-99","image":"https://assets.tcgdex.net/fr/bw/bw8/99","localId":"99","name":"Doduo"},{"id":"pl3-102","image":"https://assets.tcgdex.net/fr/pl/pl3/102","localId":"102","name":"Doduo"},{"id":"xy12-112","image":"https://assets.tcgdex.net/fr/xy/xy12/112","localId":"112","name":"Doduo d’Imakuni?"},{"id":"xy8-115","image":"https://assets.tcgdex.net/fr/xy/xy8/115","localId":"115","name":"Doduo"},{"id":"xy8-116","image":"https://assets.tcgdex.net/fr/xy/xy8/116","localId":"116","name":"Doduo"},{"id":"sm10-150","image":"https://assets.tcgdex.net/fr/sm/sm10/150","localId":"150","name":"Doduo"}],"name":"84"}