{"category":"Trainer","id":"bw9-103","illustrator":"5ban Graphics","localId":"103","name":"Recuperação de Energia Superior","rarity":"Uncommon","set":{"cardCount":{"official":116,"total":122},"id":"bw9","symbol":"https://assets.tcgdex.net/univ/bw/bw9/symbol"},"variants":{"firstEdition":false,"holo":true,"normal":true,"reverse":true},"effect":"Descarte 2 cards da sua mão. (Se você não puder descartar 2 cards, não poderá jogar esse card.) Coloque 4 cards de Energia básica da sua pilha de descarte em sua mão. (Não é possível escolher um card que foi descartado com o efeito deste card.)","trainerType":"Item","legal":{"standard":false,"expanded":true}}