{"category":"Trainer","id":"swsh7-156","illustrator":"Toyste Beach","image":"https://assets.tcgdex.net/it/swsh/swsh7/156","localId":"156","name":"Guanti di Gomma","rarity":"Uncommon","set":{"cardCount":{"official":203,"total":203},"id":"swsh7","logo":"https://assets.tcgdex.net/it/swsh/swsh7/logo","symbol":"https://assets.tcgdex.net/univ/swsh/swsh7/symbol"},"variants":{"firstEdition":false,"holo":false,"normal":true,"reverse":true},"effect":"Gli attacchi del Pokémon a cui è assegnata questa carta infliggono 30 danni in più al Pokémon attivo Lightning del tuo avversario, prima di aver applicato debolezza e resistenza.","trainerType":"Tool","legal":{"standard":true,"expanded":true}}