{"category":"Pokémon","id":"swsh5-157","illustrator":"Eske Yoshinob","localId":"157","name":"Bissbark V","rarity":"ultraselten","set":{"cardCount":{"official":202,"total":202},"id":"swsh5","name":"Kampfstile","symbol":"https://assets.tcgdex.net/univ/swsh/swsh5/symbol"},"variants":{"firstEdition":false,"holo":true,"normal":false,"reverse":false},"hp":210,"types":["Farblos"],"stage":"Basis","suffix":"V","attacks":[{"cost":["Farblos","Farblos","Farblos"],"name":"Nachbeißer","effect":"Wenn ein Basis-Pokémon deines Gegners durch Schaden dieser Attacke kampfunfähig wird, nimm 1 Preiskarte mehr.","damage":40},{"cost":["Farblos","Farblos","Farblos","Farblos"],"name":"Wilder Tackle","effect":"Dieses Pokémon fügt auch sich selbst 30 Schadenspunkte zu.","damage":200}],"weaknesses":[{"type":"Kampf","value":"×2"}],"retreat":3,"regulationMark":"E","legal":{"standard":true,"expanded":true}}