{"category":"Pokémon","id":"swsh3-100","illustrator":"Ryota Murayama","localId":"100","name":"Sleima","rarity":"Häufig","set":{"cardCount":{"official":189,"total":201},"id":"swsh3","name":"Flammende Finsternis","symbol":"https://assets.tcgdex.net/univ/swsh/swsh3/symbol"},"variants":{"firstEdition":false,"holo":false,"normal":true,"reverse":true},"hp":80,"types":["Finsternis"],"stage":"Basis","attacks":[{"cost":["Finsternis"],"name":"Davonstapfen","effect":"Lege die oberste Karte des Decks deines Gegners auf seinen Ablagestapel."},{"cost":["Finsternis","Farblos","Farblos"],"name":"Schlammstrudel","damage":50}],"weaknesses":[{"type":"Kampf","value":"×2"}],"retreat":3,"regulationMark":"D","legal":{"standard":true,"expanded":true}}