{"category":"Trainer","id":"swsh6-210","illustrator":"NC Empire","localId":"210","name":"Agathe","rarity":"Secret Rare","set":{"cardCount":{"official":190,"total":233},"id":"swsh6","name":"Schaurige Herrschaft","symbol":"https://assets.tcgdex.net/univ/swsh/swsh6/symbol"},"variants":{"firstEdition":false,"holo":true,"normal":false,"reverse":false},"effect":"Verschiebe bis zu 3 Schadensmarken von deinem Aktiven Pokémon auf das Aktive Pokémon deines Gegners.","trainerType":"Supporter","legal":{"standard":true,"expanded":true}}