{"category":"Pokémon","id":"swsh7-61","illustrator":"nagimiso","localId":"61","name":"Soporifik","rarity":"Commune","set":{"cardCount":{"official":203,"total":203},"id":"swsh7","name":"Évolution Céleste"},"variants":{"firstEdition":false,"holo":false,"normal":true,"reverse":true},"hp":70,"types":["Psy"],"stage":"De base","attacks":[{"cost":["Incolore"],"name":"Écras’Face","damage":10}],"weaknesses":[{"type":"Obscurité","value":"×2"}],"resistances":[{"type":"Combat","value":"-30"}],"retreat":2,"legal":{"standard":false,"expanded":true}}