{"cards":[{"id":"pop8-1","image":"https://assets.tcgdex.net/en/pop/pop8/1","localId":"1","name":"Heatran"},{"id":"pl4-3","image":"https://assets.tcgdex.net/en/pl/pl4/3","localId":"3","name":"Heatran"},{"id":"ru1-4","image":"https://assets.tcgdex.net/en/pl/ru1/4","localId":"4","name":"Heatran"},{"id":"dp6-6","image":"https://assets.tcgdex.net/en/dp/dp6/6","localId":"6","name":"Heatran"},{"id":"bw9-13","image":"https://assets.tcgdex.net/en/bw/bw9/13","localId":"13","name":"Heatran-EX"},{"id":"sm6-13","image":"https://assets.tcgdex.net/en/sm/sm6/13","localId":"13","name":"Heatran"},{"id":"sm11-25","image":"https://assets.tcgdex.net/en/sm/sm11/25","localId":"25","name":"Heatran GX"},{"id":"dp6-30","image":"https://assets.tcgdex.net/en/dp/dp6/30","localId":"30","name":"Heatran"},{"id":"sm8-48","image":"https://assets.tcgdex.net/en/sm/sm8/48","localId":"48","name":"Heatran"},{"id":"xy4-63","image":"https://assets.tcgdex.net/en/xy/xy4/63","localId":"63","name":"Heatran"},{"id":"sm5-88","image":"https://assets.tcgdex.net/en/sm/sm5/88","localId":"88","name":"Heatran"},{"id":"dp7-97","image":"https://assets.tcgdex.net/en/dp/dp7/97","localId":"97","name":"Heatran"},{"id":"sm7-98","image":"https://assets.tcgdex.net/en/sm/sm7/98","localId":"98","name":"Heatran"},{"id":"bw9-109","image":"https://assets.tcgdex.net/en/bw/bw9/109","localId":"109","name":"Heatran-EX"},{"id":"sm11-216","image":"https://assets.tcgdex.net/en/sm/sm11/216","localId":"216","name":"Heatran GX"},{"id":"sm11-238","image":"https://assets.tcgdex.net/en/sm/sm11/238","localId":"238","name":"Heatran GX"},{"id":"dpp-DP31","image":"https://assets.tcgdex.net/en/dp/dpp/DP31","localId":"DP31","name":"Heatran"},{"id":"smp-SM96","image":"https://assets.tcgdex.net/en/sm/smp/SM96","localId":"SM96","name":"Heatran"}],"name":"485"}