{"category":"Pokémon","id":"bw10-100","illustrator":"5ban Graphics","localId":"100","name":"Palkia-EX","rarity":"Rara Ultra","set":{"cardCount":{"official":101,"total":105},"id":"bw10","symbol":"https://assets.tcgdex.net/univ/bw/bw10/symbol"},"variants":{"firstEdition":false,"holo":true,"normal":true,"reverse":true},"dexId":[484],"hp":180,"types":["Dragón"],"suffix":"EX","attacks":[{"cost":["Incolora","Incolora","Incolora"],"damage":50},{"cost":["Planta","Agua","Incolora","Incolora"],"damage":80}],"weaknesses":[{"type":"Dragón","value":"×2"}],"retreat":2,"legal":{"standard":false,"expanded":true}}