{"category":"Pokémon","id":"xy11-72","illustrator":"Shigenori Negishi","localId":"72","name":"Kliklak","rarity":"Nicht so häufig","set":{"cardCount":{"official":114,"total":116},"id":"xy11","name":"Dampfkessel","symbol":"https://assets.tcgdex.net/univ/xy/xy11/symbol"},"variants":{"firstEdition":false,"holo":true,"normal":true,"reverse":true},"dexId":[600],"hp":80,"types":["Metall"],"stage":"Rang 1","attacks":[{"cost":["Metall","Farblos"],"name":"Klammer","damage":30},{"cost":["Metall","Metall","Farblos"],"name":"Zügelloser Überschlag","effect":"Wirf 4 Münzen. Dieser Angriff fügt 30 Schadenspunkte mal der Anzahl „Kopf“ zu.","damage":"30×"}],"weaknesses":[{"type":"Feuer","value":"×2"}],"resistances":[{"type":"Psycho","value":"-20"}],"retreat":2,"legal":{"standard":false,"expanded":true}}