{"category":"Pokemon","id":"xy12-6","illustrator":"Keiji Kinebuchi","localId":"6","name":"Kakuna","rarity":"Uncommon","set":{"cardCount":{"official":108,"total":113},"id":"xy12","name":"Evoluzioni","symbol":"https://assets.tcgdex.net/univ/xy/xy12/symbol"},"variants":{"firstEdition":false,"holo":true,"normal":true,"reverse":true},"dexId":[14],"hp":80,"types":["Grass"],"stage":"Stage1","attacks":[{"cost":["Colorless","Colorless"],"name":"Indurimento","effect":"Durante il prossimo turno del tuo avversario, i danni inflitti a questo Pokémon dagli attacchi sono ridotti di 40, dopo aver applicato debolezza e resistenza."},{"cost":["Grass","Grass"],"name":"Velenpolvere","effect":"Lancia una moneta. Se esce testa, il Pokémon attivo del tuo avversario viene avvelenato.","damage":20}],"weaknesses":[{"type":"Fire","value":"×2"}],"retreat":2,"legal":{"standard":false,"expanded":true}}