{"cards":[{"id":"det1-2","image":"https://assets.tcgdex.net/en/sm/det1/2","localId":"2","name":"Ludicolo"},{"id":"det1-5","image":"https://assets.tcgdex.net/en/sm/det1/5","localId":"5","name":"Charizard"},{"id":"det1-7","image":"https://assets.tcgdex.net/en/sm/det1/7","localId":"7","name":"Psyduck"},{"id":"det1-8","image":"https://assets.tcgdex.net/en/sm/det1/8","localId":"8","name":"Magikarp"},{"id":"det1-14","image":"https://assets.tcgdex.net/en/sm/det1/14","localId":"14","name":"Jigglypuff"},{"id":"det1-15","image":"https://assets.tcgdex.net/en/sm/det1/15","localId":"15","name":"Snubbull"},{"id":"det1-18","image":"https://assets.tcgdex.net/en/sm/det1/18","localId":"18","name":"Slaking"},{"id":"smp-SM195","localId":"SM195","name":"Charizard GX"}],"name":"Framestore"}