{"category":"Pokémon","id":"sm6-22","illustrator":"Aya Kusube","localId":"22","name":"Froxy","rarity":"Häufig","set":{"cardCount":{"official":131,"total":146},"id":"sm6","name":"Grauen Der Lichtfinsternis","symbol":"https://assets.tcgdex.net/univ/sm/sm6/symbol"},"variants":{"firstEdition":false,"holo":true,"normal":true,"reverse":true},"dexId":[656],"hp":70,"types":["Wasser"],"stage":"Basis","attacks":[{"cost":["Wasser"],"name":"Regenplatscher","damage":10},{"cost":["Wasser","Farblos"],"name":"Wellenplatscher","damage":20}],"weaknesses":[{"type":"Pflanze","value":"×2"}],"retreat":1,"legal":{"standard":false,"expanded":true}}