{"category":"Pokemon","id":"xy11-9","illustrator":"sui","localId":"9","name":"Seedot","rarity":"Common","set":{"cardCount":{"official":114,"total":116},"id":"xy11","symbol":"https://assets.tcgdex.net/univ/xy/xy11/symbol"},"variants":{"firstEdition":false,"holo":true,"normal":true,"reverse":true},"dexId":[273],"hp":50,"types":["Grass"],"stage":"Basic","attacks":[{"cost":["Grass"],"name":"Aguardar","effect":"Jogue uma moeda. Se sair cara, se este Pokémon estiver prestes a ser Nocauteado por danos causados por um ataque durante a próxima vez de jogar do seu oponente, ele não será Nocauteado e o seu PS restante se tornará 10."}],"weaknesses":[{"type":"Fire","value":"×2"}],"retreat":1,"legal":{"standard":false,"expanded":true}}