{"cards":[{"id":"sm8-45","image":"https://assets.tcgdex.net/fr/sm/sm8/45","localId":"45","name":"Malosse"},{"id":"hgss3-53","localId":"53","name":"Malosse"},{"id":"hgss3-54","localId":"54","name":"Malosse"},{"id":"bw10-55","image":"https://assets.tcgdex.net/fr/bw/bw10/55","localId":"55","name":"Malosse"},{"id":"sm4-58","image":"https://assets.tcgdex.net/fr/sm/sm4/58","localId":"58","name":"Malosse"},{"id":"dp4-69","localId":"69","name":"Malosse"},{"id":"bw6-74","image":"https://assets.tcgdex.net/fr/bw/bw6/74","localId":"74","name":"Malosse"},{"id":"dp6-103","localId":"103","name":"Malosse"}],"name":"228"}