{"category":"Pokémon","id":"sm8-72","illustrator":"Akira Komayama","localId":"72","name":"Electivire","rarity":"Rara","set":{"cardCount":{"official":214,"total":236},"id":"sm8","name":"Tuoni Perduti","symbol":"https://assets.tcgdex.net/univ/sm/sm8/symbol"},"variants":{"firstEdition":false,"holo":true,"normal":true,"reverse":true},"dexId":[466],"hp":140,"types":["Lampo"],"stage":"Livello 1","attacks":[{"cost":["Incolore"],"name":"Carica Voltaica","effect":"Cerca nel tuo mazzo fino a due carte Energia Lightning e assegnale a questo Pokémon. Poi rimischia le carte del tuo mazzo."},{"cost":["Lampo","Lampo","Lampo","Incolore"],"name":"Pugno Folgorante","effect":"Scarta tre Energie assegnate a questo Pokémon.","damage":190}],"weaknesses":[{"type":"Lotta","value":"×2"}],"resistances":[{"type":"Metallo","value":"-20"}],"retreat":4,"legal":{"standard":false,"expanded":true}}