{"cards":[{"id":"dp6-4","image":"https://assets.tcgdex.net/en/dp/dp6/4","localId":"4","name":"Giratina"},{"id":"pl1-9","image":"https://assets.tcgdex.net/en/pl/pl1/9","localId":"9","name":"Giratina"},{"id":"pl1-10","image":"https://assets.tcgdex.net/en/pl/pl1/10","localId":"10","name":"Giratina"},{"id":"pl1-27","image":"https://assets.tcgdex.net/en/pl/pl1/27","localId":"27","name":"Giratina"},{"id":"pl1-28","image":"https://assets.tcgdex.net/en/pl/pl1/28","localId":"28","name":"Giratina"},{"id":"xy7-57","image":"https://assets.tcgdex.net/en/xy/xy7/57","localId":"57","name":"Giratina EX"},{"id":"sm5-58","image":"https://assets.tcgdex.net/en/sm/sm5/58","localId":"58","name":"Giratina ◇"},{"id":"bw8-62","image":"https://assets.tcgdex.net/en/bw/bw8/62","localId":"62","name":"Giratina"},{"id":"sm11-86","image":"https://assets.tcgdex.net/en/sm/sm11/86","localId":"86","name":"Giratina"},{"id":"bw6-92","image":"https://assets.tcgdex.net/en/bw/bw6/92","localId":"92","name":"Giratina-EX"},{"id":"xy7-93","image":"https://assets.tcgdex.net/en/xy/xy7/93","localId":"93","name":"Giratina EX"},{"id":"sm8-97","image":"https://assets.tcgdex.net/en/sm/sm8/97","localId":"97","name":"Giratina"},{"id":"bw6-124","image":"https://assets.tcgdex.net/en/bw/bw6/124","localId":"124","name":"Giratina-EX"},{"id":"pl1-124","image":"https://assets.tcgdex.net/en/pl/pl1/124","localId":"124","name":"Giratina"},{"id":"bwp-BW74","image":"https://assets.tcgdex.net/en/bw/bwp/BW74","localId":"BW74","name":"Giratina"},{"id":"dpp-DP38","image":"https://assets.tcgdex.net/en/dp/dpp/DP38","localId":"DP38","name":"Giratina"},{"id":"smp-SM151","image":"https://assets.tcgdex.net/en/sm/smp/SM151","localId":"SM151","name":"Giratina"},{"id":"xyp-XY184","image":"https://assets.tcgdex.net/en/xy/xyp/XY184","localId":"XY184","name":"Giratina"}],"name":"487"}