{"category":"Pokemon","id":"bw1-29","illustrator":"Masakazu Fukuda","localId":"29","name":"Dewott","rarity":"Uncommon","set":{"cardCount":{"official":114,"total":115},"id":"bw1","name":"Nero e Bianco","symbol":"https://assets.tcgdex.net/univ/bw/bw1/symbol"},"variants":{"firstEdition":false,"holo":true,"normal":true,"reverse":true},"dexId":[502],"hp":90,"types":["Water"],"stage":"Stage1","attacks":[{"cost":["Colorless","Colorless"],"damage":30},{"cost":["Water","Water","Colorless"],"damage":40}],"weaknesses":[{"type":"Lightning","value":"×2"}],"retreat":1,"legal":{"standard":false,"expanded":true}}