{"category":"Pokémon","id":"bw4-29","illustrator":"Akira Komayama","localId":"29","name":"Sodachita","rarity":"Keine","set":{"cardCount":{"official":99,"total":103},"id":"bw4","name":"Kommende Schicksale","symbol":"https://assets.tcgdex.net/univ/bw/bw4/symbol"},"variants":{"firstEdition":false,"holo":true,"normal":true,"reverse":true},"dexId":[516],"hp":90,"types":["Wasser"],"stage":"Rang 1","attacks":[{"cost":["Wasser"]},{"cost":["Wasser","Farblos"],"damage":30}],"weaknesses":[{"type":"Elektro","value":"×2"}],"retreat":1,"legal":{"standard":false,"expanded":true}}