{"cards":[{"id":"bw7-2","localId":"2","name":"Duflor"},{"id":"sm8-2","localId":"2","name":"Tangoloss"},{"id":"swsh3-3","localId":"3","name":"Paras"},{"id":"xy10-5","localId":"5","name":"Serpifeu"},{"id":"swsh1-7","localId":"7","name":"Maracamba"},{"id":"bw8-8","localId":"8","name":"Strawickl"},{"id":"bw2-9","localId":"9","name":"Waumboll"},{"id":"bw1-10","localId":"10","name":"Dressella"},{"id":"sm3-10","localId":"10","name":"Ledian"},{"id":"sm9-12","localId":"12","name":"Glumanda"},{"id":"bw1-13","localId":"13","name":"Sesokitz"},{"id":"bw5-15","localId":"15","name":"Flemmli"},{"id":"sm6-15","localId":"15","name":"Fynx"},{"id":"bw4-17","localId":"17","name":"Flampion"},{"id":"bw8-19","localId":"19","name":"Grillmak"},{"id":"sm7-19","localId":"19","name":"Tuska"},{"id":"sm7-20","localId":"20","name":"Noktuska"},{"id":"bw3-22","localId":"22","name":"Schallquap"},{"id":"bw9-22","localId":"22","name":"Morlord"},{"id":"bw6-25","localId":"25","name":"Wailmer"},{"id":"bw2-27","localId":"27","name":"Swaroness"},{"id":"bw3-27","localId":"27","name":"Gelatini"},{"id":"sm6-27","localId":"27","name":"Amarino"},{"id":"sm10-27","localId":"27","name":"Flamiau"},{"id":"sm1-31","localId":"31","name":"Quaputzi"},{"id":"bw1-33","localId":"33","name":"Sodamak"},{"id":"bw4-36","localId":"36","name":"Petznief"},{"id":"sm7-36","localId":"36","name":"Loturzel"},{"id":"xy9-36","localId":"36","name":"Piccolente"},{"id":"sm7-37","localId":"37","name":"Lombrero"},{"id":"sm7-38","localId":"38","name":"Kappalores"},{"id":"bw6-39","localId":"39","name":"Waaty"},{"id":"bw9-41","localId":"41","name":"Nidorina"},{"id":"bw4-42","localId":"42","name":"Sheinux"},{"id":"bw2-45","localId":"45","name":"Hypnomorba"},{"id":"bw1-48","localId":"48","name":"Somniam"},{"id":"sm11-48","localId":"48","name":"Araqua"},{"id":"bw3-50","localId":"50","name":"Monozyto"},{"id":"bw6-60","localId":"60","name":"Tragosso"},{"id":"bw2-64","localId":"64","name":"Felilou"},{"id":"sm4-66","localId":"66","name":"Stollrak"},{"id":"sm8-66","localId":"66","name":"Marikeck"},{"id":"sm9-66","localId":"66","name":"Pantimos"},{"id":"bw3-70","localId":"70","name":"Wie-Shu"},{"id":"sm4-75","localId":"75","name":"Miniras"},{"id":"bw7-80","localId":"80","name":"Skorgla"},{"id":"sm12-80","localId":"80","name":"Trasla"},{"id":"bw9-81","localId":"81","name":"Dratini"},{"id":"swsh5-81","localId":"81","name":"Salanga"},{"id":"sm1-83","localId":"83","name":"Ganovil"},{"id":"bw2-84","localId":"84","name":"Picochilla"},{"id":"bw3-86","localId":"86","name":"Milza"},{"id":"bw5-88","localId":"88","name":"Bissbark"},{"id":"xy11-91","localId":"91","name":"Ambidiffel"},{"id":"sm6-93","localId":"93","name":"Viscargot"},{"id":"sm3-95","localId":"95","name":"Wommel"},{"id":"swsh7-96","localId":"96","name":"Blanas"},{"id":"bw8-97","localId":"97","name":"Piepi"},{"id":"swsh2-99","localId":"99","name":"Schmerbe"},{"id":"sm5-104","localId":"104","name":"Evoli"},{"id":"sm11-108","localId":"108","name":"Kapilz"},{"id":"swsh4-114","localId":"114","name":"Forstellka"},{"id":"bw7-118","localId":"118","name":"Nagelotz"},{"id":"sm10-121","localId":"121","name":"Alola-Digda"},{"id":"swsh4-131","localId":"131","name":"Relaxo"},{"id":"sm12-150","localId":"150","name":"Flabébé"},{"id":"sm10-205","localId":"205","name":"Guardevoir & Feelinara GX"}],"name":"Atsuko Nishida"}