{"category":"Pokémon","id":"sm2-83","illustrator":"Kyoko Umemoto","localId":"83","name":"Tanhel","rarity":"Häufig","set":{"cardCount":{"official":145,"total":169},"id":"sm2","name":"Stunde der Wächter","symbol":"https://assets.tcgdex.net/univ/sm/sm2/symbol"},"variants":{"firstEdition":false,"holo":true,"normal":true,"reverse":true},"dexId":[374],"hp":60,"types":["Metall"],"stage":"Basis","attacks":[{"cost":["Metall"],"name":"Kernstrahl","effect":"Lege 1 Metal-Energie von diesem Pokémon auf deinen Ablagestapel.","damage":20}],"weaknesses":[{"type":"Feuer","value":"×2"}],"resistances":[{"type":"Psycho","value":"-20"}],"retreat":1,"legal":{"standard":false,"expanded":true}}