{"category":"Pokemon","id":"xy10-31","illustrator":"Sanosuke Sakuma","localId":"31","name":"Groink","rarity":"Rare","set":{"cardCount":{"official":124,"total":125},"id":"xy10","name":"Schicksalsschmiede","symbol":"https://assets.tcgdex.net/univ/xy/xy10/symbol"},"variants":{"firstEdition":false,"holo":true,"normal":true,"reverse":true},"dexId":[326],"hp":100,"types":["Psychic"],"stage":"Stage1","attacks":[{"cost":["Psychic"],"name":"Kopflauf","effect":"Nimm 1 Basis-Pokémon aus dem Ablagestapel deines Gegners und lege es auf seine Bank. Lege anschließend 3 Schadensmarken auf jenes Pokémon."},{"cost":["Psychic","Psychic"],"name":"Schlag versetzen","effect":"Dein Gegner tauscht sein Aktives Pokémon gegen 1 Pokémon auf seiner Bank aus.","damage":50}],"weaknesses":[{"type":"Psychic","value":"×2"}],"retreat":2,"legal":{"standard":false,"expanded":true}}