{"category":"Pokemon","id":"cel25-25","illustrator":"Saki Hayashiro","localId":"25","name":"Mew","rarity":"Secret Rare","set":{"cardCount":{"official":50,"total":51},"id":"cel25","logo":"https://assets.tcgdex.net/en/swsh/cel25/logo","name":"Celebrations"},"variants":{"firstEdition":false,"holo":false,"normal":false,"reverse":false},"hp":60,"types":["Psychic"],"stage":"Basic","abilities":[{"type":"Ability","name":"Mysterious Tail","effect":"Once during your turn, if this Pokémon is in the Active Spot, you may look at the top 6 cards of your deck, reveal an Item card you find there, and put it into your hand. Shuffle the other cards back into your deck."}],"attacks":[{"cost":["Psychic","Colorless"],"name":"Psyshot","damage":"30"}],"weaknesses":[{"type":"Darkness","value":"×2"}],"resistances":[{"type":"Fighting","value":"-30"}],"retreat":1,"legal":{"standard":false,"expanded":true}}