{"category":"Pokémon","id":"xy11-92","illustrator":"Mitsuhiro Arita","localId":"92","name":"Geronimatz","rarity":"Häufig","set":{"cardCount":{"official":114,"total":116},"id":"xy11","name":"Dampfkessel","symbol":"https://assets.tcgdex.net/univ/xy/xy11/symbol"},"variants":{"firstEdition":false,"holo":true,"normal":true,"reverse":true},"dexId":[627],"hp":60,"types":["Farblos"],"stage":"Basis","attacks":[{"cost":["Farblos"],"name":"Waghalsiger Sturmangriff","effect":"Dieses Pokémon fügt sich selbst 10 Schadenspunkte zu.","damage":20}],"weaknesses":[{"type":"Elektro","value":"×2"}],"resistances":[{"type":"Kampf","value":"-20"}],"retreat":1,"legal":{"standard":false,"expanded":true}}