{"category":"Trainer","id":"bw1-93","illustrator":"Ryo Ueda","localId":"93","name":"Ricerca di Energia","rarity":"Common","set":{"cardCount":{"official":114,"total":115},"id":"bw1","name":"Nero e Bianco","symbol":"https://assets.tcgdex.net/univ/bw/bw1/symbol"},"variants":{"firstEdition":false,"holo":true,"normal":true,"reverse":true},"effect":"Cerca nel tuo mazzo una carta Energia base, mostrala e aggiungila a quelle che hai in mano. Poi rimischia le carte del tuo mazzo.","trainerType":"Item","legal":{"standard":false,"expanded":true}}