{"category":"Pokémon","id":"xy10-82","illustrator":"Masakazu Fukuda","localId":"82","name":"Krawumms","rarity":"Keine","set":{"cardCount":{"official":124,"total":125},"id":"xy10","name":"Schicksalsschmiede","symbol":"https://assets.tcgdex.net/univ/xy/xy10/symbol"},"variants":{"firstEdition":false,"holo":true,"normal":true,"reverse":true},"dexId":[295],"hp":140,"types":["Farblos"],"stage":"Rang 2","attacks":[{"cost":["Farblos","Farblos","Farblos"],"name":"Hinterhalt","effect":"Wirf 1 Münze. Bei „Kopf“ fügt dieser Angriff 40 weitere Schadenspunkte zu.","damage":"80+"},{"cost":["Farblos","Farblos","Farblos"],"name":"Kakofonie","effect":"Lege am Ende des nächsten Zuges deines Gegners das Verteidigende Pokémon und alle daran angelegten Karten auf dessen Ablagestapel."}],"weaknesses":[{"type":"Kampf","value":"×2"}],"retreat":3,"legal":{"standard":false,"expanded":true}}