{"category":"Trainer","id":"bw1-96","illustrator":"5ban Graphics","localId":"96","name":"PlusPower","rarity":"Uncommon","set":{"cardCount":{"official":114,"total":115},"id":"bw1","name":"Schwarz & Weiß","symbol":"https://assets.tcgdex.net/univ/bw/bw1/symbol"},"variants":{"firstEdition":false,"holo":true,"normal":true,"reverse":true},"effect":"Während dieses Zuges fügen alle Angriffe deines Pokémon den Aktiven Pokémon 10 weitere Schadenspunkte zu (bevor Schwäche und Resistenz verrechnet werden).","trainerType":"Item","legal":{"standard":false,"expanded":true}}