{"cards":[{"id":"sm115-13","localId":"13","name":"Stari"},{"id":"sm4-15","image":"https://assets.tcgdex.net/fr/sm/sm4/15","localId":"15","name":"Stari"},{"id":"bw4-23","image":"https://assets.tcgdex.net/fr/bw/bw4/23","localId":"23","name":"Stari"},{"id":"xy9-25","image":"https://assets.tcgdex.net/fr/xy/xy9/25","localId":"25","name":"Stari"},{"id":"sm9-28","image":"https://assets.tcgdex.net/fr/sm/sm9/28","localId":"28","name":"Stari"},{"id":"xy8-29","image":"https://assets.tcgdex.net/fr/xy/xy8/29","localId":"29","name":"Stari"},{"id":"xy12-30","image":"https://assets.tcgdex.net/fr/xy/xy12/30","localId":"30","name":"Stari"},{"id":"xy5-32","image":"https://assets.tcgdex.net/fr/xy/xy5/32","localId":"32","name":"Stari"},{"id":"xy1-33","image":"https://assets.tcgdex.net/fr/xy/xy1/33","localId":"33","name":"Stari"},{"id":"pl2-83","image":"https://assets.tcgdex.net/fr/pl/pl2/83","localId":"83","name":"Stari Niv. 18"},{"id":"hgss1-84","localId":"84","name":"Stari"},{"id":"dp6-122","localId":"122","name":"Stari"}],"name":"120"}