{"category":"Pokémon","id":"sm10-41","illustrator":"Shigenori Negishi","localId":"41","name":"Tentacruel","rarity":"Non comune","set":{"cardCount":{"official":214,"total":234},"id":"sm10","name":"Legami Inossidabili","symbol":"https://assets.tcgdex.net/univ/sm/sm10/symbol"},"variants":{"firstEdition":false,"holo":true,"normal":true,"reverse":true},"dexId":[73],"hp":100,"types":["Acqua"],"stage":"Livello 1","attacks":[{"cost":["Incolore"],"name":"Tentacoli Malefici","effect":"Sposta un’Energia da uno dei Pokémon del tuo avversario a un altro dei suoi Pokémon. Se lo fai, metti tre segnalini danno sul Pokémon sul quale hai spostato l’Energia."},{"cost":["Incolore","Incolore","Incolore"],"name":"Avvolgibotta","effect":"Lancia una moneta. Se esce testa, il Pokémon attivo del tuo avversario viene paralizzato.","damage":60}],"weaknesses":[{"type":"Erba","value":"×2"}],"retreat":1,"legal":{"standard":false,"expanded":true}}