{"category":"Pokémon","id":"xy11-49","illustrator":"miki kudo","localId":"49","name":"Laternecto","rarity":"Nicht so häufig","set":{"cardCount":{"official":114,"total":116},"id":"xy11","name":"Dampfkessel","symbol":"https://assets.tcgdex.net/univ/xy/xy11/symbol"},"variants":{"firstEdition":false,"holo":true,"normal":true,"reverse":true},"dexId":[608],"hp":80,"types":["Psycho"],"stage":"Rang 1","attacks":[{"cost":["Farblos"],"name":"Spieglein, Spieglein","effect":"Jeder Spieler muss so viele Karten ziehen oder ablegen, bis der Spieler 4 Karten auf der Hand hat. (Dein Gegner beginnt.)"},{"cost":["Psycho","Farblos"],"name":"Züngelnde Flammen","effect":"Das Aktive Pokémon deines Gegners schläft jetzt.","damage":20}],"weaknesses":[{"type":"Finsternis","value":"×2"}],"resistances":[{"type":"Kampf","value":"-20"}],"retreat":1,"legal":{"standard":false,"expanded":true}}