{"category":"Trainer","id":"xy12-108","illustrator":"Megumi Mizutani","localId":"108","name":"Determinação da Misty","rarity":"Ultra Rare","set":{"cardCount":{"official":108,"total":113},"id":"xy12","symbol":"https://assets.tcgdex.net/univ/xy/xy12/symbol"},"variants":{"firstEdition":false,"holo":true,"normal":true,"reverse":true},"effect":"Descarte um card da sua mão. Se fizer isso, olhe os 8 cards de cima do seu baralho e coloque 1 deles na sua mão. Embaralhe os demais cards de volta no seu baralho.","trainerType":"Supporter","legal":{"standard":false,"expanded":true}}