{"category":"Pokemon","id":"xy11-64","illustrator":"Shin Nagasawa","localId":"64","name":"Bisharp","rarity":"Rare","set":{"cardCount":{"official":114,"total":116},"id":"xy11","name":"Vapori Accesi","symbol":"https://assets.tcgdex.net/univ/xy/xy11/symbol"},"variants":{"firstEdition":false,"holo":true,"normal":true,"reverse":true},"dexId":[625],"hp":100,"types":["Darkness","Metal"],"stage":"Stage1","attacks":[{"cost":["Colorless"],"name":"Nemesi","effect":"Se uno qualsiasi dei tuoi Pokémon è stato messo KO dai danni inflitti da un attacco del tuo avversario durante il suo ultimo turno, questo attacco infligge 60 danni in più.","damage":"30+"},{"cost":["Darkness","Colorless"],"name":"Artiglio Mach","effect":"I danni di questo attacco non sono influenzati dalla resistenza.","damage":60}],"weaknesses":[{"type":"Fighting","value":"×2"}],"resistances":[{"type":"Psychic","value":"-20"}],"retreat":2,"legal":{"standard":false,"expanded":true}}