{"category":"Pokémon","id":"bw3-6","illustrator":"MAHOU","localId":"6","name":"Dwebble","rarity":"Commún","set":{"cardCount":{"official":101,"total":102},"id":"bw3","name":"Nobles Victorias","symbol":"https://assets.tcgdex.net/univ/bw/bw3/symbol"},"variants":{"firstEdition":false,"holo":true,"normal":true,"reverse":true},"dexId":[557],"hp":60,"types":["Planta"],"stage":"Basico","attacks":[{"cost":["Incolora"]},{"cost":["Planta","Incolora"],"damage":20}],"weaknesses":[{"type":"Guego","value":"×2"}],"retreat":2,"legal":{"standard":false,"expanded":true}}