{"category":"Pokémon","id":"bw2-53","illustrator":"Naoki Saito","localId":"53","name":"Brockoloss","rarity":"Keine","set":{"cardCount":{"official":98,"total":98},"id":"bw2","name":"Aufstreben der Mächtigen","symbol":"https://assets.tcgdex.net/univ/bw/bw2/symbol"},"variants":{"firstEdition":false,"holo":true,"normal":true,"reverse":true},"dexId":[526],"hp":140,"types":["Kampf"],"stage":"Rang 2","attacks":[{"cost":["Kampf"]},{"cost":["Farblos","Farblos","Farblos","Farblos"],"damage":40}],"weaknesses":[{"type":"Pflanze","value":"×2"}],"retreat":4,"legal":{"standard":false,"expanded":true}}