{"cards":[{"id":"sm6-49","image":"https://assets.tcgdex.net/en/sm/sm6/49","localId":"49","name":"Aegislash"},{"id":"xy9-62","image":"https://assets.tcgdex.net/en/xy/xy9/62","localId":"62","name":"Aegislash"},{"id":"xy4-65","image":"https://assets.tcgdex.net/en/xy/xy4/65","localId":"65","name":"Aegislash EX"},{"id":"xy4-65a","image":"https://assets.tcgdex.net/en/xy/xy4/65a","localId":"65a","name":"Aegislash-EX"},{"id":"xy1-85","image":"https://assets.tcgdex.net/en/xy/xy1/85","localId":"85","name":"Aegislash"},{"id":"xy1-86","image":"https://assets.tcgdex.net/en/xy/xy1/86","localId":"86","name":"Aegislash"},{"id":"sm11-95","image":"https://assets.tcgdex.net/en/sm/sm11/95","localId":"95","name":"Aegislash"},{"id":"xy5-100","image":"https://assets.tcgdex.net/en/xy/xy5/100","localId":"100","name":"Aegislash"},{"id":"sm9-109","image":"https://assets.tcgdex.net/en/sm/sm9/109","localId":"109","name":"Aegislash"}],"name":"681"}