{"category":"Pokémon","id":"bw9-96","illustrator":"sui","localId":"96","name":"Staravia","rarity":"Nicht so häufig","set":{"cardCount":{"official":116,"total":122},"id":"bw9","name":"Plasma-Frost","symbol":"https://assets.tcgdex.net/univ/bw/bw9/symbol"},"variants":{"firstEdition":false,"holo":true,"normal":true,"reverse":true},"dexId":[397],"hp":80,"types":["Farblos"],"stage":"Rang 1","attacks":[{"cost":["Farblos","Farblos"],"damage":30}],"weaknesses":[{"type":"Elektro","value":"×2"}],"resistances":[{"type":"Kampf","value":"-20"}],"retreat":1,"legal":{"standard":false,"expanded":true}}