{"category":"Pokémon","id":"bw9-18","illustrator":"Midori Harada","localId":"18","name":"Seeper","rarity":"Häufig","set":{"cardCount":{"official":116,"total":122},"id":"bw9","name":"Plasma-Frost","symbol":"https://assets.tcgdex.net/univ/bw/bw9/symbol"},"variants":{"firstEdition":false,"holo":true,"normal":true,"reverse":true},"dexId":[116],"hp":60,"types":["Wasser"],"stage":"Basis","attacks":[{"cost":["Wasser"],"damage":10}],"weaknesses":[{"type":"Elektro","value":"×2"}],"retreat":1,"legal":{"standard":false,"expanded":true}}