{"category":"Pokémon","id":"xy11-10","illustrator":"Ayaka Yoshida","localId":"10","name":"Nuzleaf","rarity":"Non comune","set":{"cardCount":{"official":114,"total":116},"id":"xy11","name":"Vapori Accesi","symbol":"https://assets.tcgdex.net/univ/xy/xy11/symbol"},"variants":{"firstEdition":false,"holo":true,"normal":true,"reverse":true},"dexId":[274],"hp":70,"types":["Erba"],"stage":"Livello 1","attacks":[{"cost":["Erba"],"name":"Rafforzatore","effect":"Durante il prossimo turno del tuo avversario, se questo Pokémon sta per essere danneggiato da un attacco, previeni i danni di quell’attacco inflitti a questo Pokémon se quei danni sono 60 o meno."},{"cost":["Incolore","Incolore"],"name":"Foglielama","damage":20}],"weaknesses":[{"type":"Fuoco","value":"×2"}],"retreat":1,"legal":{"standard":false,"expanded":true}}