{"category":"Pokémon","id":"sm6-4","illustrator":"Masakazu Fukuda","localId":"4","name":"Rexblisar","rarity":"Keine","set":{"cardCount":{"official":131,"total":146},"id":"sm6","name":"Grauen Der Lichtfinsternis","symbol":"https://assets.tcgdex.net/univ/sm/sm6/symbol"},"variants":{"firstEdition":false,"holo":true,"normal":true,"reverse":true},"dexId":[460],"hp":130,"types":["Pflanze"],"stage":"Rang 1","abilities":[{"type":"Ability","name":"Segen des Frostes","effect":"Wenn du dieses Pokémon aus deiner Hand spielst, um 1 deiner Pokémon während deines Zuges zu entwickeln, kannst du 1 Grass-Energiekarte aus deinem Ablagestapel an 1 deiner Pokémon anlegen."}],"attacks":[{"cost":["Pflanze","Farblos","Farblos","Farblos"],"name":"Hypnohammer","effect":"Das Aktive Pokémon deines Gegners schläft jetzt.","damage":80}],"weaknesses":[{"type":"Feuer","value":"×2"}],"retreat":3,"legal":{"standard":false,"expanded":true}}