{"cards":[{"id":"xy0-6","image":"https://assets.tcgdex.net/fr/xy/xy0/6","localId":"6","name":"Limagma"},{"id":"xy1-20","image":"https://assets.tcgdex.net/fr/xy/xy1/20","localId":"20","name":"Limagma"},{"id":"xy5-22","image":"https://assets.tcgdex.net/fr/xy/xy5/22","localId":"22","name":"Limagma"},{"id":"sm7-23","image":"https://assets.tcgdex.net/fr/sm/sm7/23","localId":"23","name":"Limagma"},{"id":"sm12-26","image":"https://assets.tcgdex.net/fr/sm/sm12/26","localId":"26","name":"Limagma"},{"id":"sm8-43","image":"https://assets.tcgdex.net/fr/sm/sm8/43","localId":"43","name":"Limagma"},{"id":"hgss3-67","localId":"67","name":"Limagma"},{"id":"dp4-83","localId":"83","name":"Limagma"}],"name":"218"}