{"category":"Pokémon","id":"sm1-112","illustrator":"kirisAki","localId":"112","name":"Kosturso","rarity":"Keine","set":{"cardCount":{"official":149,"total":163},"id":"sm1","name":"Sonne & Mond","symbol":"https://assets.tcgdex.net/univ/sm/sm1/symbol"},"variants":{"firstEdition":false,"holo":true,"normal":true,"reverse":true},"dexId":[760],"hp":130,"types":["Farblos"],"stage":"Rang 1","attacks":[{"cost":["Farblos","Farblos"],"name":"Dicke Umarmung","effect":"Das Verteidigende Pokémon kann sich während des nächsten Zuges deines Gegners nicht zurückziehen.","damage":40},{"cost":["Farblos","Farblos","Farblos"],"name":"Kraftkoloss","effect":"Du kannst 40 Schadenspunkte mehr zufügen. Wenn du das machst, fügt dieses Pokémon sich selbst 20 Schadenspunkte zu.","damage":"80+"}],"weaknesses":[{"type":"Kampf","value":"×2"}],"retreat":3,"legal":{"standard":false,"expanded":true}}