{"category":"Pokémon","id":"swsh7-115","illustrator":"hatachu","image":"https://assets.tcgdex.net/es/swsh/swsh7/115","localId":"115","name":"Hydreigon","rarity":"Rara","set":{"cardCount":{"official":203,"total":203},"id":"swsh7","logo":"https://assets.tcgdex.net/es/swsh/swsh7/logo","name":"Cielos Evolutivos","symbol":"https://assets.tcgdex.net/univ/swsh/swsh7/symbol"},"variants":{"firstEdition":false,"holo":true,"normal":false,"reverse":true},"hp":170,"types":["Dragón"],"stage":"Fase 2","attacks":[{"cost":["Psíquico","Oscura"],"name":"Contraataque Dragón","effect":"Este ataque hace 100 puntos de daño más por cada carta de Premio que haya cogido tu rival durante su último turno.","damage":"20+"},{"cost":["Psíquico","Oscura","Incolora","Incolora"],"name":"Colmillos Azabaches","damage":210}],"retreat":3,"legal":{"standard":false,"expanded":true}}