{"category":"Dresseur","id":"bw5-98","illustrator":"Kanako Eo","image":"https://assets.tcgdex.net/fr/bw/bw5/98","localId":"98","name":"Professeur Keteleeria","rarity":"Peu Commune","set":{"cardCount":{"official":108,"total":111},"id":"bw5","logo":"https://assets.tcgdex.net/fr/bw/bw5/logo","name":"Explorateurs Obscurs","symbol":"https://assets.tcgdex.net/univ/bw/bw5/symbol"},"variants":{"firstEdition":false,"holo":true,"normal":true,"reverse":true},"effect":"Défaussez votre main et piochez 7 cartes.","trainerType":"Supporter","legal":{"standard":false,"expanded":true}}