{"cards":[{"id":"hgss2-29","localId":"29","name":"Insolourdo"},{"id":"hgss1-41","localId":"41","name":"Insolourdo"},{"id":"xy6-68","image":"https://assets.tcgdex.net/fr/xy/xy6/68","localId":"68","name":"Insolourdo"},{"id":"pl1-73","image":"https://assets.tcgdex.net/fr/pl/pl1/73","localId":"73","name":"Insolourdo"},{"id":"xy9-90","image":"https://assets.tcgdex.net/fr/xy/xy9/90","localId":"90","name":"Insolourdo"},{"id":"xy1-101","image":"https://assets.tcgdex.net/fr/xy/xy1/101","localId":"101","name":"Insolourdo"},{"id":"sm7-110","image":"https://assets.tcgdex.net/fr/sm/sm7/110","localId":"110","name":"Insolourdo"},{"id":"bw7-111","image":"https://assets.tcgdex.net/fr/bw/bw7/111","localId":"111","name":"Insolourdo"}],"name":"206"}