{"cards":[{"id":"bw2-88","image":"https://assets.tcgdex.net/en/bw/bw2/88","localId":"88","name":"Braviary"},{"id":"xy11-93","image":"https://assets.tcgdex.net/en/xy/xy11/93","localId":"93","name":"Braviary"},{"id":"bw6-112","image":"https://assets.tcgdex.net/en/bw/bw6/112","localId":"112","name":"Braviary"},{"id":"bw8-116","image":"https://assets.tcgdex.net/en/bw/bw8/116","localId":"116","name":"Braviary"},{"id":"xy8-130","image":"https://assets.tcgdex.net/en/xy/xy8/130","localId":"130","name":"Braviary"},{"id":"sm12-178","image":"https://assets.tcgdex.net/en/sm/sm12/178","localId":"178","name":"Braviary"}],"name":"628"}