{"category":"Trainer","id":"xy12-87","illustrator":"Keiji Kinebuchi","image":"https://assets.tcgdex.net/en/xy/xy12/87","localId":"87","name":"Super Potion","rarity":"Uncommon","set":{"cardCount":{"official":108,"total":113},"id":"xy12","logo":"https://assets.tcgdex.net/en/xy/xy12/logo","name":"Evolutions","symbol":"https://assets.tcgdex.net/univ/xy/xy12/symbol"},"variants":{"firstEdition":false,"holo":true,"normal":true,"reverse":true},"effect":"Heal 60 damage from 1 of your Pokémon. If you do, discard an Energy attached to that Pokémon.","trainerType":"Item","legal":{"standard":false,"expanded":true}}