{"category":"Trainer","id":"xy11-102","illustrator":"Toyste Beach","localId":"102","name":"Dado Ganancioso","rarity":"Uncommon","set":{"cardCount":{"official":114,"total":116},"id":"xy11","symbol":"https://assets.tcgdex.net/univ/xy/xy11/symbol"},"variants":{"firstEdition":false,"holo":true,"normal":true,"reverse":true},"effect":"Você pode jogar este card somente se o pegou dos seus cards de Prêmio virados para baixo, antes de colocá-lo na sua mão.Jogue uma moeda. Se sair cara, pegue mais 1 card de Prêmio.","trainerType":"Item","legal":{"standard":false,"expanded":true}}