{"category":"Pokémon","id":"swsh4-27","illustrator":"Mina Nakai","localId":"27","name":"Slugma","rarity":"Comune","set":{"cardCount":{"official":185,"total":203},"id":"swsh4","name":"Voltaggio Sfolgorante","symbol":"https://assets.tcgdex.net/univ/swsh/swsh4/symbol"},"variants":{"firstEdition":false,"holo":false,"normal":true,"reverse":true},"hp":70,"types":["Fuoco"],"stage":"Base","attacks":[{"cost":["Incolore"],"name":"Sbadiglio","effect":"Il Pokémon attivo del tuo avversario viene addormentato."},{"cost":["Fuoco","Incolore","Incolore"],"name":"Fiammata","damage":30}],"weaknesses":[{"type":"Acqua","value":"×2"}],"retreat":2,"regulationMark":"D","legal":{"standard":true,"expanded":true}}