{"category":"Pokémon","id":"bw7-2","illustrator":"Atsuko Nishida","localId":"2","name":"Duflor","rarity":"Nicht so häufig","set":{"cardCount":{"official":149,"total":153},"id":"bw7","name":"Überschrittene Schwellen","symbol":"https://assets.tcgdex.net/univ/bw/bw7/symbol"},"variants":{"firstEdition":false,"holo":true,"normal":true,"reverse":true},"dexId":[44],"hp":80,"types":["Pflanze"],"stage":"Rang 1","attacks":[{"cost":["Farblos","Farblos"]},{"cost":["Pflanze","Farblos","Farblos"],"damage":40}],"weaknesses":[{"type":"Feuer","value":"×2"}],"resistances":[{"type":"Wasser","value":"-20"}],"retreat":1,"legal":{"standard":false,"expanded":true}}