{"category":"Energy","id":"bw4-93","illustrator":"5ban Graphics","localId":"93","name":"Energia Prisma","rarity":"Uncommon","set":{"cardCount":{"official":99,"total":103},"id":"bw4","name":"Destini Futuri","symbol":"https://assets.tcgdex.net/univ/bw/bw4/symbol"},"variants":{"firstEdition":false,"holo":true,"normal":true,"reverse":true},"effect":"Questa carta fornisce Colorless. Se il Pokémon a cui è assegnata questa carta è un Pokémon Base, questa carta fornisce un’Energia di un tipo qualsiasi, ma solo una alla volta.","energyType":"Special","legal":{"standard":false,"expanded":true}}