{"category":"Pokémon","id":"sm10-98","illustrator":"Ken Sugimori","localId":"98","name":"Skorgla","rarity":"Häufig","set":{"cardCount":{"official":214,"total":234},"id":"sm10","name":"Kräfte im Einklang","symbol":"https://assets.tcgdex.net/univ/sm/sm10/symbol"},"variants":{"firstEdition":false,"holo":true,"normal":true,"reverse":true},"dexId":[207],"hp":60,"types":["Kampf"],"stage":"Basis","abilities":[{"type":"Ability","name":"Freiflug","effect":"Wenn an dieses Pokémon keine Energie angelegt ist, hat dieses Pokémon keine Rückzugskosten."}],"attacks":[{"cost":["Farblos","Farblos","Farblos"],"name":"Shinobi-Schlag","effect":"Wenn du Janina während dieses Zuges aus deiner Hand gespielt hast, fügt diese Attacke 90 Schadenspunkte mehr zu.","damage":"30+"}],"weaknesses":[{"type":"Pflanze","value":"×2"}],"retreat":2,"legal":{"standard":false,"expanded":true}}