{"category":"Pokémon","id":"swsh7-32","illustrator":"Teeziro","image":"https://assets.tcgdex.net/es/swsh/swsh7/32","localId":"32","name":"Lotad","rarity":"Commún","set":{"cardCount":{"official":203,"total":203},"id":"swsh7","logo":"https://assets.tcgdex.net/es/swsh/swsh7/logo","symbol":"https://assets.tcgdex.net/univ/swsh/swsh7/symbol"},"variants":{"firstEdition":false,"holo":false,"normal":true,"reverse":true},"hp":60,"types":["Agua"],"stage":"Basico","attacks":[{"cost":["Incolora"],"name":"Llamar a la Familia","effect":"Busca en tu baraja hasta 2 Pokémon Básicos y ponlos en tu Banca. Después, baraja las cartas de tu baraja."},{"cost":["Agua","Incolora"],"name":"Golpe de Lluvia","damage":20}],"weaknesses":[{"type":"Rayo","value":"×2"}],"retreat":1,"legal":{"standard":true,"expanded":true}}