{"category":"Trainer","id":"swsh7-148","illustrator":"AYUMI ODASHIMA","image":"https://assets.tcgdex.net/de/swsh/swsh7/148","localId":"148","name":"Gesichtsschutz","rarity":"Uncommon","set":{"cardCount":{"official":203,"total":203},"id":"swsh7","logo":"https://assets.tcgdex.net/de/swsh/swsh7/logo","name":"Drachenwandel","symbol":"https://assets.tcgdex.net/univ/swsh/swsh7/symbol"},"variants":{"firstEdition":false,"holo":false,"normal":true,"reverse":true},"effect":"Wenn das Pokémon, an das diese Karte angelegt ist, keine Fähigkeiten hat, werden ihm durch Attacken der Pokémon deines Gegners 20 Schadenspunkte weniger zugefügt (nachdem Schwäche und Resistenz verrechnet wurden).","trainerType":"Tool","legal":{"standard":false,"expanded":true}}