{"category":"Trainer","id":"swsh7-201","illustrator":"Hitoshi Ariga","image":"https://assets.tcgdex.net/it/swsh/swsh7/201","localId":"201","name":"Milo","rarity":"Ultra Rare","set":{"cardCount":{"official":203,"total":203},"id":"swsh7","logo":"https://assets.tcgdex.net/it/swsh/swsh7/logo","name":"Evoluzioni Eteree","symbol":"https://assets.tcgdex.net/univ/swsh/swsh7/symbol"},"variants":{"firstEdition":false,"holo":false,"normal":false,"reverse":false},"effect":"Guarda le prime sette carte del tuo mazzo. Puoi mostrare un numero qualsiasi di carte Energia presenti tra esse e aggiungerle alle carte che hai in mano. Poi rimischia le altre carte nel tuo mazzo.","trainerType":"Supporter","legal":{"standard":false,"expanded":true}}