{"category":"Pokémon","id":"bw8-91","illustrator":"5ban Graphics","localId":"91","name":"Fermicula","rarity":"Nicht so häufig","set":{"cardCount":{"official":135,"total":138},"id":"bw8","name":"Plasma-Sturm","symbol":"https://assets.tcgdex.net/univ/bw/bw8/symbol"},"variants":{"firstEdition":false,"holo":true,"normal":true,"reverse":true},"dexId":[632],"hp":70,"types":["Metall"],"stage":"Basis","attacks":[{"cost":["Farblos","Farblos"],"damage":20},{"cost":["Metall","Farblos","Farblos"],"damage":40}],"weaknesses":[{"type":"Feuer","value":"×2"}],"resistances":[{"type":"Psycho","value":"-20"}],"retreat":1,"legal":{"standard":false,"expanded":true}}