{"category":"Pokémon","id":"bw6-42","illustrator":"Masakazu Fukuda","localId":"42","name":"Electrike","rarity":"Comune","set":{"cardCount":{"official":124,"total":128},"id":"bw6","name":"Stirpe dei Draghi","symbol":"https://assets.tcgdex.net/univ/bw/bw6/symbol"},"variants":{"firstEdition":false,"holo":true,"normal":true,"reverse":true},"dexId":[309],"hp":60,"types":["Lampo"],"stage":"Base","attacks":[{"cost":["Lampo","Incolore"],"damage":20}],"weaknesses":[{"type":"Lotta","value":"×2"}],"retreat":1,"legal":{"standard":false,"expanded":true}}