{"category":"Pokémon","id":"sm12-3","illustrator":"sui","localId":"3","name":"Duflor","rarity":"Nicht so häufig","set":{"cardCount":{"official":236,"total":271},"id":"sm12","name":"Welten im Wandel","symbol":"https://assets.tcgdex.net/univ/sm/sm12/symbol"},"variants":{"firstEdition":false,"holo":true,"normal":true,"reverse":true},"dexId":[44],"hp":80,"types":["Pflanze"],"stage":"Rang 1","attacks":[{"cost":["Pflanze"],"name":"Schlafpuder","effect":"Das Aktive Pokémon deines Gegners schläft jetzt.","damage":20}],"weaknesses":[{"type":"Feuer","value":"×2"}],"retreat":2,"legal":{"standard":false,"expanded":true}}