{"category":"Pokémon","id":"xy10-8","illustrator":"Kanako Eo","localId":"8","name":"Sesokitz","rarity":"Häufig","set":{"cardCount":{"official":124,"total":125},"id":"xy10","name":"Schicksalsschmiede","symbol":"https://assets.tcgdex.net/univ/xy/xy10/symbol"},"variants":{"firstEdition":false,"holo":true,"normal":true,"reverse":true},"dexId":[585],"hp":60,"types":["Pflanze"],"stage":"Basis","attacks":[{"cost":["Farblos"],"name":"Freunde finden","effect":"Durchsuche dein Deck nach 1 Pokémon, zeige es deinem Gegner und nimm es auf deine Hand. Mische anschließend dein Deck."}],"weaknesses":[{"type":"Feuer","value":"×2"}],"retreat":1,"legal":{"standard":false,"expanded":true}}