{"category":"Pokémon","id":"sm2-91","illustrator":"Kouki Saitou","localId":"91","name":"Whimsicott","rarity":"Non comune","set":{"cardCount":{"official":145,"total":169},"id":"sm2","name":"Guardiani Nascenti","symbol":"https://assets.tcgdex.net/univ/sm/sm2/symbol"},"variants":{"firstEdition":false,"holo":true,"normal":true,"reverse":true},"dexId":[547],"hp":80,"types":["Folletto"],"stage":"Livello 1","attacks":[{"cost":["Incolore"],"name":"Prezzo della Morbidezza","effect":"Se il Pokémon difensore viene messo KO durante il tuo prossimo turno, prendi due carte Premio in più."},{"cost":["Folletto"],"name":"Vento di Fata","damage":30}],"weaknesses":[{"type":"Metallo","value":"×2"}],"resistances":[{"type":"Oscurità","value":"-20"}],"retreat":0,"legal":{"standard":false,"expanded":true}}