{"category":"Trainer","id":"bw7-130","illustrator":"Yusuke Ohmura","image":"https://assets.tcgdex.net/en/bw/bw7/130","localId":"130","name":"Hugh","rarity":"Uncommon","set":{"cardCount":{"official":149,"total":153},"id":"bw7","logo":"https://assets.tcgdex.net/en/bw/bw7/logo","name":"Boundaries Crossed","symbol":"https://assets.tcgdex.net/univ/bw/bw7/symbol"},"variants":{"firstEdition":false,"holo":true,"normal":true,"reverse":true},"effect":"Each player either draws or discards cards until he or she has 5 cards in his or her hand. (Your opponent does this first.)","trainerType":"Supporter","legal":{"standard":false,"expanded":true}}