{"category":"Pokémon","id":"swsh3-119","illustrator":"5ban Graphics","localId":"119","name":"Scherox VMAX","rarity":"ultraselten","set":{"cardCount":{"official":189,"total":201},"id":"swsh3","name":"Flammende Finsternis","symbol":"https://assets.tcgdex.net/univ/swsh/swsh3/symbol"},"variants":{"firstEdition":false,"holo":true,"normal":false,"reverse":false},"hp":320,"types":["Metall"],"stage":"VMAX","attacks":[{"cost":["Metall","Farblos"],"name":"Harte Scheren","effect":"Während des nächsten Zuges deines Gegners werden diesem Pokémon durch Attacken 30 Schadenspunkte weniger zugefügt (nachdem Schwäche und Resistenz verrechnet wurden).","damage":90},{"cost":["Metall","Metall","Farblos"],"name":"Dyna-Stahlzacken","damage":190}],"weaknesses":[{"type":"Feuer","value":"×2"}],"resistances":[{"type":"Pflanze","value":"-30"}],"retreat":2,"regulationMark":"D","legal":{"standard":true,"expanded":true}}