{"category":"Trainer","id":"bw5-101","illustrator":"Ryo Ueda","localId":"101","name":"Wendelberg","rarity":"Nicht so häufig","set":{"cardCount":{"official":108,"total":111},"id":"bw5","name":"Erfoscher der Finsternis","symbol":"https://assets.tcgdex.net/univ/bw/bw5/symbol"},"variants":{"firstEdition":false,"holo":true,"normal":true,"reverse":true},"effect":"Einmal während seines Zuges darf jeder Spieler 1 Münze werfen. Bei „Kopf“ durchsucht der Spieler sein Deck nach 1 Erweckt-Pokémon und legt es auf seine Bank.","trainerType":"Stadionkarte","legal":{"standard":false,"expanded":true}}